[
  {
    "id": 1,
    "user_id": "mohannadezzzahra@gmail.com",
    "deduction_name": "insurance",
    "deduction_amount": 353.0,
    "annual_income": 500000.0,
    "social_security_contributions": 233.0,
    "tax_credits": 0.0,
    "calculation_date": "2025-02-28T10:26:37.009Z",
    "tax_amount": 99745.5,
    "is_monthly": false,
    "monthly_income": 0.0,
    "monthly_deduction": 0.0,
    "monthly_social_security": 0.0,
    "monthly_tax_amount": 0.0
  },
  {
    "id": 2,
    "user_id": "mohannadezzzahra@gmail.com",
    "deduction_name": "insurance",
    "deduction_amount": 353.0,
    "annual_income": 500000.0,
    "social_security_contributions": 233.0,
    "tax_credits": 0.0,
    "calculation_date": "2025-02-28T10:28:08.726Z",
    "tax_amount": 99745.5,
    "is_monthly": false,
    "monthly_income": 0.0,
    "monthly_deduction": 0.0,
    "monthly_social_security": 0.0,
    "monthly_tax_amount": 0.0
  },
  {
    "id": 3,
    "user_id": "mohannadezzzahra@gmail.com",
    "deduction_name": "medical",
    "deduction_amount": 123.0,
    "annual_income": 1231312312.0,
    "social_security_contributions": 123.0,
    "tax_credits": 0.0,
    "calculation_date": "2025-02-28T10:33:24.739Z",
    "tax_amount": 338555945.15000004,
    "is_monthly": false,
    "monthly_income": 0.0,
    "monthly_deduction": 0.0,
    "monthly_social_security": 0.0,
    "monthly_tax_amount": 0.0
  },
  {
    "id": 4,
    "user_id": "mohannadezzzahra@gmail.com",
    "deduction_name": "education",
    "deduction_amount": 234.0,
    "annual_income": 123456.0,
    "social_security_contributions": 23.0,
    "tax_credits": 0.0,
    "calculation_date": "2025-02-28T10:38:38.263Z",
    "tax_amount": 14864.800000000001,
    "is_monthly": false,
    "monthly_income": 0.0,
    "monthly_deduction": 0.0,
    "monthly_social_security": 0.0,
    "monthly_tax_amount": 0.0
  },
  {
    "id": 5,
    "user_id": "mohannadezzzahra@gmail.com",
    "deduction_name": "medical",
    "deduction_amount": 1313.0,
    "annual_income": 121312312.0,
    "social_security_contributions": 123.0,
    "tax_credits": 0.0,
    "calculation_date": "2025-02-28T10:47:45.981Z",
    "tax_amount": 33305617.900000002,
    "is_monthly": false,
    "monthly_income": 0.0,
    "monthly_deduction": 0.0,
    "monthly_social_security": 0.0,
    "monthly_tax_amount": 0.0
  },
  {
    "id": 6,
    "user_id": "mohannadezzzahra@gmail.com",
    "deduction_name": "charity",
    "deduction_amount": 1234.0,
    "annual_income": 123334.0,
    "social_security_contributions": 123.0,
    "tax_credits": 0.0,
    "calculation_date": "2025-02-28T10:55:07.971Z",
    "tax_amount": 14522.400000000001,
    "is_monthly": false,
    "monthly_income": 0.0,
    "monthly_deduction": 0.0,
    "monthly_social_security": 0.0,
    "monthly_tax_amount": 0.0
  }
]